README.md
setup.py
bin/collider
collider/__init__.py
collider/iteration.py
collider/predicates.py
collider/resultlog.py
collider/stage.py
collider/version.py
collider.egg-info/PKG-INFO
collider.egg-info/SOURCES.txt
collider.egg-info/dependency_links.txt
collider.egg-info/not-zip-safe
collider.egg-info/requires.txt
collider.egg-info/top_level.txt