Metadata-Version: 1.0
Name: collider
Version: 0.3.1
Summary: A software experimenting framework
Home-page: https://gitlab.com/dreval/collider
Author: Dimitri Scheftelowitsch
Author-email: dimitri.scheftelowitsch@tu-dortmund.de
License: APL 2.0
Platform: UNKNOWN
